{"adult":false,"backdrop_path":null,"belongs_to_collection":null,"budget":0,"genres":[{"id":80,"name":"Crime"},{"id":53,"name":"Thriller"}],"homepage":"","id":1100289,"imdb_id":"tt26931771","original_language":"en","original_title":"On Point","overview":"Natalie and her roommate Amy head to a party downtown. While waiting for a cab, Amy stops to buy a vape when she's confronted by an armed man with an agenda.","popularity":0.6,"poster_path":null,"production_companies":[{"id":195819,"logo_path":null,"name":"Pimlico Pictures","origin_country":""}],"production_countries":[],"release_date":"","revenue":0,"runtime":7,"spoken_languages":[],"status":"In Production","tagline":"","title":"On Point","video":false,"vote_average":0.0,"vote_count":0}