{"adult":false,"backdrop_path":"/mIlzrzaCFwr5fdXB5ASnLuouTju.jpg","belongs_to_collection":null,"budget":0,"genres":[{"id":18,"name":"Drama"}],"homepage":"","id":1108580,"imdb_id":"tt23863694","original_language":"ta","original_title":"காரோட்டியின் காதலி","overview":"A cab driver gets caught between the internal affairs of a shady Singaporean businessman who has other plans in place","popularity":0.719,"poster_path":"/mmnmRtrZD0KJ65ZNMe0A8oNBYq3.jpg","production_companies":[{"id":197070,"logo_path":null,"name":"3S Pictures","origin_country":"IN"}],"production_countries":[{"iso_3166_1":"IN","name":"India"}],"release_date":"2022-11-18","revenue":0,"runtime":101,"spoken_languages":[{"english_name":"Tamil","iso_639_1":"ta","name":"தமிழ்"}],"status":"Released","tagline":"","title":"Kaarottiyin Kaadhali","video":false,"vote_average":0.0,"vote_count":0}