{"adult":false,"backdrop_path":null,"belongs_to_collection":null,"budget":0,"genres":[{"id":99,"name":"Documentary"}],"homepage":"","id":1127815,"imdb_id":"tt6736216","original_language":"en","original_title":"3rd Reich: Hitler's UFOs and the Nazi's Most Powerful Weapon","overview":"The Nazi's possessed technology that was 100 years ahead of the allies. After being captured, many top scientists and psychiatrists of the elite Nazi regime, admitted that an outside force assisted them, and that the 3rd Reich's ultimate mandate was to create \"the most powerful weapon.\" Hitler's UFO's is the story of the Nazis and the Aliens from outer space. Dark Secrets of the Nazis: Researchers now believe WWII was the result of a massive, worldwide conspiracy by an elusive secret society known as the Illuminati. A secret sect so powerful they not only control economics and politics, but may very well be involved in manipulating society itself via advanced technology; while controlling staggering secret knowledge not shared with anyone, including the heads of nations.","popularity":0.6,"poster_path":null,"production_companies":[],"production_countries":[],"release_date":"2017-04-11","revenue":0,"runtime":150,"spoken_languages":[],"status":"Released","tagline":"","title":"3rd Reich: Hitler's UFOs and the Nazi's Most Powerful Weapon","video":false,"vote_average":10.0,"vote_count":1}