{"adult":false,"backdrop_path":null,"belongs_to_collection":null,"budget":0,"genres":[{"id":14,"name":"Fantasy"},{"id":10751,"name":"Family"},{"id":10770,"name":"TV Movie"},{"id":12,"name":"Adventure"}],"homepage":"","id":209346,"imdb_id":"tt0076497","original_language":"en","original_title":"Once Upon a Brothers Grimm","overview":"While traveling to meet with the Hessian King, the famed Brothers Grimm, Jacob and Wilhelm, travel through an enchanted forest where they find themselves trapped in the world of their fairy tales.","popularity":1.202,"poster_path":"/sgqDR2dGCrUWPgyQq10rElPKIbK.jpg","production_companies":[{"id":21618,"logo_path":null,"name":"Rothman/Wohl Productions","origin_country":""}],"production_countries":[{"iso_3166_1":"US","name":"United States of America"}],"release_date":"1977-11-23","revenue":0,"runtime":103,"spoken_languages":[{"english_name":"English","iso_639_1":"en","name":"English"}],"status":"Released","tagline":"","title":"Once Upon a Brothers Grimm","video":false,"vote_average":0.0,"vote_count":0}