{"adult":false,"backdrop_path":null,"belongs_to_collection":null,"budget":0,"genres":[{"id":99,"name":"Documentary"}],"homepage":"","id":215342,"imdb_id":"tt1050233","original_language":"cn","original_title":"0506HK","overview":"Quentin Lee returns to Hong Kong, where he was born and raised. As he explores his desire to move back there from Los Angeles, he interviews local artists, filmmakers, friends, and family about why they are in Hong Kong and why they choose to be there.","popularity":0.6,"poster_path":"/d8TfFUk8DumiBxA7fvIxYgzcvCA.jpg","production_companies":[{"id":71972,"logo_path":null,"name":"Margin Films","origin_country":""},{"id":19178,"logo_path":null,"name":"Ying E Chi","origin_country":""}],"production_countries":[],"release_date":"2007-07-06","revenue":0,"runtime":63,"spoken_languages":[{"english_name":"Cantonese","iso_639_1":"cn","name":"广州话 / 廣州話"},{"english_name":"English","iso_639_1":"en","name":"English"}],"status":"Released","tagline":"","title":"0506HK","video":false,"vote_average":0.0,"vote_count":0}