{"adult":false,"backdrop_path":"/6VnCwqkNOiWUp9v5BpPsUqp0ayu.jpg","belongs_to_collection":null,"budget":0,"genres":[{"id":18,"name":"Drama"},{"id":878,"name":"Science Fiction"},{"id":10770,"name":"TV Movie"},{"id":53,"name":"Thriller"}],"homepage":"","id":222870,"imdb_id":"tt0116319","original_language":"en","original_title":"Subliminal Seduction","overview":"Darrin Danver is married to Deb. He is a videogames programmer and works for Z-Games when he receives an offer for a job from CTC. He accepts the offer and moves with his wife Deb near Las Vegas. There he discovers that he is paid a lot only to develop the videogame Radical Rat Trap, which is to follow Amazing Mouse Maze. But the great family of CTC uses Videogames Cd-Rom and subliminal messages to try to control minds, his and his wife's.","popularity":2.718,"poster_path":"/eJg1Ydb0IXAysmRglZBFtwnHvaA.jpg","production_companies":[{"id":4688,"logo_path":null,"name":"Concorde-New Horizons","origin_country":"US"},{"id":11130,"logo_path":null,"name":"Royal Oaks Entertainment Inc.","origin_country":""},{"id":4343,"logo_path":"/rXq1B1Hnkdnw6soz1zoGcslK3wb.png","name":"Showtime Networks","origin_country":"US"}],"production_countries":[{"iso_3166_1":"US","name":"United States of America"}],"release_date":"1996-01-28","revenue":0,"runtime":81,"spoken_languages":[{"english_name":"English","iso_639_1":"en","name":"English"}],"status":"Released","tagline":"","title":"Subliminal Seduction","video":false,"vote_average":3.2,"vote_count":5}