{"adult":false,"backdrop_path":null,"belongs_to_collection":null,"budget":0,"genres":[],"homepage":"","id":235701,"imdb_id":"tt2951876","original_language":"en","original_title":"Sunday Morning","overview":"On Sunday morning a nine year old girl is getting up to all sorts around her palatial home. After a scary experience in the swimming pool, Kiva has an encounter with a visiting window cleaner. But can he be trusted? And where are her parents?","popularity":0.6,"poster_path":"/2YNw3Sg3D6SBJuM11Jc6qq5ioBp.jpg","production_companies":[],"production_countries":[],"release_date":"2012-01-01","revenue":0,"runtime":25,"spoken_languages":[],"status":"Released","tagline":"","title":"Sunday Morning","video":false,"vote_average":5.0,"vote_count":3}