{"adult":false,"backdrop_path":null,"belongs_to_collection":null,"budget":0,"genres":[],"homepage":"","id":266836,"imdb_id":"tt0085967","original_language":"en","original_title":"Les mots pour le dire","overview":"Based on an autobiographical novel by Marie Cardinal, this well-acted psychological drama details the tormented relationship between Marie (Nicole Garcia) and her mother, stemming from Marie's childhood on their estate in Algeria. The mother, Eliane (Marie-Christine Barrault) had lost a child before Marie was born, and was consumed with hatred for her husband who was carrying tuberculosis and may have been the cause of the child's death. That hatred was never resolved, and Marie grew up in a bitter and strained household. As both women grow older, Marie marries and raises a family while her mother sinks ever deeper into anger, frustration, poverty, and isolated despair. She vents her destructive emotions on her daughter and is completely resistent to her daughter's attempts to help her, to make her life better.","popularity":0.6,"poster_path":"/7eH2zJXnlSx0lkJzafGgg4qUgCU.jpg","production_companies":[],"production_countries":[],"release_date":"1983-10-12","revenue":0,"runtime":92,"spoken_languages":[],"status":"Released","tagline":"","title":"Les mots pour le dire","video":false,"vote_average":6.5,"vote_count":2}