{"adult":false,"backdrop_path":"/i1srD8yJAEOkwN2L29lCesDjT5B.jpg","belongs_to_collection":null,"budget":32000000,"genres":[{"id":28,"name":"Action"},{"id":14,"name":"Fantasy"},{"id":10749,"name":"Romance"}],"homepage":"","id":299822,"imdb_id":"tt3585004","original_language":"zh","original_title":"钟馗伏魔：雪妖魔灵","overview":"The story of Chinese legendary anti-hero Zhong Kui, a young man endowed with mysterious powers who is forced into a battle among the realms of Heaven, Earth and Hell in the course of his attempt to save his countrymen and the woman he loves.","popularity":7.673,"poster_path":"/q6UYtxTxpN68PCzjQ86cVX8t8CL.jpg","production_companies":[{"id":4053,"logo_path":null,"name":"Enlight Pictures","origin_country":"CN"},{"id":22839,"logo_path":"/uySsPIA5PdoccIUxomkw0cfgBjB.png","name":"Village Roadshow Pictures Asia","origin_country":""},{"id":74457,"logo_path":null,"name":"Tencent Video","origin_country":"CN"},{"id":78948,"logo_path":null,"name":"Wu's Entertainment Co.","origin_country":""},{"id":78949,"logo_path":null,"name":"Desen International Media","origin_country":""},{"id":78950,"logo_path":null,"name":"K Pictures Co.","origin_country":""},{"id":78951,"logo_path":null,"name":"Tianhua Xiuxing Media Co.","origin_country":""},{"id":78952,"logo_path":null,"name":"Wanda Media Co.","origin_country":"CN"},{"id":174,"logo_path":"/IuAlhI9eVC9Z8UQWOIDdWRKSEJ.png","name":"Warner Bros. Pictures","origin_country":"US"}],"production_countries":[{"iso_3166_1":"US","name":"United States of America"},{"iso_3166_1":"CN","name":"China"},{"iso_3166_1":"HK","name":"Hong Kong"}],"release_date":"2015-02-19","revenue":0,"runtime":118,"spoken_languages":[{"english_name":"Mandarin","iso_639_1":"zh","name":"普通话"}],"status":"Released","tagline":"","title":"Zhongkui: Snow Girl and the Dark Crystal","video":false,"vote_average":5.25,"vote_count":36}