{"adult":false,"backdrop_path":"/361RR4mJrniWHQgiWsmcOoDc4qP.jpg","belongs_to_collection":{"id":997736,"name":"Single Collection","poster_path":"/soZtyqLWhvWvRrnW8pgiD7HatBU.jpg","backdrop_path":null},"budget":0,"genres":[{"id":18,"name":"Drama"},{"id":35,"name":"Comedy"},{"id":10749,"name":"Romance"}],"homepage":"","id":373758,"imdb_id":"tt5169582","original_language":"id","original_title":"Single","overview":"Unemployed and immature, a somewhat pathetic bachelor sets his sights on finding a date for the wedding of his younger, more successful brother.","popularity":1.021,"poster_path":"/68ugYqT6ydkQgFdlFaqEEks092Y.jpg","production_companies":[{"id":16514,"logo_path":null,"name":"Soraya Intercine Films","origin_country":"ID"}],"production_countries":[{"iso_3166_1":"ID","name":"Indonesia"}],"release_date":"2015-12-17","revenue":0,"runtime":127,"spoken_languages":[{"english_name":"Indonesian","iso_639_1":"id","name":"Bahasa indonesia"}],"status":"Released","tagline":"","title":"Single","video":false,"vote_average":6.6,"vote_count":4}