{"adult":false,"backdrop_path":null,"belongs_to_collection":null,"budget":0,"genres":[{"id":35,"name":"Comedy"}],"homepage":"","id":391865,"imdb_id":"tt2481500","original_language":"en","original_title":"Playin' for Love","overview":"Coach Banks (Robert Townsend) is used to calling all the shots for his championship high school basketball team and in his own love life. But that’s about to change when he meets, Talisa McCoy (Salli Richardson-Whitfield), the mother of a star player, new to Jackson high. She’s a beautiful, strong-willed single mom, with her own ideas on a winning team…and the perfect man. Now, this coach will have to learn a few new plays if he’s going to stay in the game.","popularity":0.708,"poster_path":"/ybrF5JhXHlSMRE4TRcEEgXMLOuC.jpg","production_companies":[],"production_countries":[],"release_date":"2015-01-16","revenue":0,"runtime":84,"spoken_languages":[{"english_name":"English","iso_639_1":"en","name":"English"}],"status":"Released","tagline":"An arrogant high school coach has his life turned upside down when a superstar player transfers to the school and his mother tries to take over the team.","title":"Playin' for Love","video":false,"vote_average":5.0,"vote_count":2}