{"adult":false,"backdrop_path":null,"belongs_to_collection":null,"budget":0,"genres":[{"id":878,"name":"Science Fiction"}],"homepage":"","id":392032,"imdb_id":"tt4933974","original_language":"en","original_title":"Artificial Intelligence","overview":"A woman finds herself being coerced into a robotic-related scientific breakthrough. She struggles to take control, but at what cost? Inspired by the Portal video games, and written by a teenager for the Pens to Lens film festival.","popularity":0.626,"poster_path":"/yjPqAN2g7IGg2nq6zeXZCdCGpG5.jpg","production_companies":[],"production_countries":[{"iso_3166_1":"US","name":"United States of America"}],"release_date":"2015-10-04","revenue":0,"runtime":11,"spoken_languages":[{"english_name":"English","iso_639_1":"en","name":"English"}],"status":"Released","tagline":"They did it... for science.","title":"Artificial Intelligence","video":false,"vote_average":6.5,"vote_count":1}