{"adult":false,"backdrop_path":"/bJF3XFy5TofDqo5C6iYhAa0Qcg.jpg","belongs_to_collection":null,"budget":0,"genres":[{"id":28,"name":"Action"},{"id":12,"name":"Adventure"}],"homepage":"","id":398622,"imdb_id":"tt5246410","original_language":"zh","original_title":"心跳戈壁","overview":"Wild Desert has enough ingredients to be a cool enough action movie.","popularity":0.6,"poster_path":"/9rgeAt0sE7YAIxeOrzq1XMMmy0F.jpg","production_companies":[],"production_countries":[{"iso_3166_1":"CN","name":"China"}],"release_date":"2015-05-22","revenue":0,"runtime":93,"spoken_languages":[{"english_name":"Mandarin","iso_639_1":"zh","name":"普通话"}],"status":"Released","tagline":"","title":"Wild Desert","video":false,"vote_average":3.5,"vote_count":1}