{"adult":false,"backdrop_path":null,"belongs_to_collection":null,"budget":0,"genres":[],"homepage":"","id":445225,"imdb_id":"","original_language":"en","original_title":"Chuckle Brothers: Indiana Chuckles And The Kingdom Of The Mythical Sulk","overview":"Paul and Barry set off for Morocco in search of an old treasure map which is being used as a table cloth in a restaurant and end up on a mad-cap adventure.","popularity":0.6,"poster_path":null,"production_companies":[{"id":29604,"logo_path":null,"name":"Liberation Entertainment","origin_country":""}],"production_countries":[{"iso_3166_1":"GB","name":"United Kingdom"}],"release_date":"2008-09-22","revenue":0,"runtime":90,"spoken_languages":[{"english_name":"English","iso_639_1":"en","name":"English"}],"status":"Released","tagline":"","title":"Chuckle Brothers: Indiana Chuckles And The Kingdom Of The Mythical Sulk","video":true,"vote_average":0.0,"vote_count":0}