{"adult":false,"backdrop_path":null,"belongs_to_collection":null,"budget":0,"genres":[{"id":35,"name":"Comedy"}],"homepage":"","id":508181,"imdb_id":"tt0028948","original_language":"de","original_title":"Gordian, der Tyrann","overview":"Film by Fred Sauer.","popularity":0.6,"poster_path":"/v5U1LCS4Jx9h9Ttx1HHzgwCq9eX.jpg","production_companies":[],"production_countries":[{"iso_3166_1":"DE","name":"Germany"}],"release_date":"1937-06-19","revenue":0,"runtime":100,"spoken_languages":[],"status":"Released","tagline":"","title":"Gordian, der Tyrann","video":false,"vote_average":0.0,"vote_count":0}