{"adult":false,"backdrop_path":null,"belongs_to_collection":null,"budget":0,"genres":[{"id":18,"name":"Drama"},{"id":16,"name":"Animation"},{"id":14,"name":"Fantasy"},{"id":36,"name":"History"}],"homepage":"","id":518419,"imdb_id":"tt1520963","original_language":"en","original_title":"Junko's Shamisen","overview":"A young Japanese orphan, and her mystical friend, exact poetic justice on a malevolent samurai lord.","popularity":0.6,"poster_path":"/Ajyck6xY99RRuBjssUcsVXpnmWD.jpg","production_companies":[{"id":24725,"logo_path":"/1HhNIJjQO2enpg76YNryXBWribp.png","name":"Ontario Arts Council","origin_country":"CA"}],"production_countries":[{"iso_3166_1":"CA","name":"Canada"}],"release_date":"2010-01-24","revenue":0,"runtime":11,"spoken_languages":[{"english_name":"English","iso_639_1":"en","name":"English"},{"english_name":"Japanese","iso_639_1":"ja","name":"日本語"}],"status":"Released","tagline":"","title":"Junko's Shamisen","video":false,"vote_average":5.7,"vote_count":3}