{"adult":false,"backdrop_path":"/1zgugDjeC24ip242hEETR9CaUar.jpg","belongs_to_collection":null,"budget":0,"genres":[{"id":35,"name":"Comedy"},{"id":27,"name":"Horror"}],"homepage":"","id":576004,"imdb_id":"tt8485772","original_language":"en","original_title":"Porno","overview":"When a group of naive teens working at a movie theater in a small Christian town discover a mysterious film hidden in its basement, they unleash an alluring succubus who gives them a sex education…written in blood.","popularity":32.532,"poster_path":"/1X6BxBlHqA8VdFrLwmeSiNSEpEB.jpg","production_companies":[{"id":87327,"logo_path":null,"name":"Evoke","origin_country":""},{"id":137628,"logo_path":"/7fNQ8e7oXpOSwz43WesfAIyVAbu.png","name":"Cranked Up Films","origin_country":"US"},{"id":108781,"logo_path":"/kHAIsNbR9DEiupDXYnloc9FyZl7.png","name":"Cinestate","origin_country":"US"}],"production_countries":[{"iso_3166_1":"US","name":"United States of America"}],"release_date":"2019-06-28","revenue":0,"runtime":98,"spoken_languages":[{"english_name":"English","iso_639_1":"en","name":"English"}],"status":"Released","tagline":"If you use it, you'll lose it...","title":"Porno","video":false,"vote_average":6.247,"vote_count":285}