{"adult":false,"backdrop_path":"/48NsG8gdbjHwMxn042bAti6iFQU.jpg","belongs_to_collection":null,"budget":0,"genres":[{"id":18,"name":"Drama"}],"homepage":"","id":587121,"imdb_id":"tt9496212","original_language":"hi","original_title":"२२ यार्ड्स","overview":"Ron Sen is a successful sports agent who manages top players from the Indian cricket team. After controversy ends the prospects of his career, Ron mentors a down-on-luck cricketer, Shome to help achieve his dream.","popularity":1.001,"poster_path":"/xVzkEz7LxpDJirzYfh0UfGbT16O.jpg","production_companies":[{"id":5762,"logo_path":null,"name":"M.S. Productions","origin_country":""}],"production_countries":[],"release_date":"2019-03-15","revenue":0,"runtime":140,"spoken_languages":[{"english_name":"Hindi","iso_639_1":"hi","name":"हिन्दी"}],"status":"Released","tagline":"","title":"22 Yards","video":false,"vote_average":10.0,"vote_count":1}