{"adult":false,"backdrop_path":"/hPOs5NhnR9SQpCIE7qx2EXSfsv6.jpg","belongs_to_collection":null,"budget":0,"genres":[{"id":99,"name":"Documentary"}],"homepage":"","id":590219,"imdb_id":"tt10045136","original_language":"en","original_title":"War of Art","overview":"What happens when a group of international artists travel to North Korea to create art like the regime have never seen before? While the world is on the verge of nuclear war, a group of Western contemporary artists are invited into the eye of the storm. The aim is to collaborate with North Korean artists in a creative exchange project displaying new and challenging art in a country where abstract art is forbidden.","popularity":0.84,"poster_path":"/dDZJvyTErXFJeIm3vghbg3xskkb.jpg","production_companies":[{"id":92604,"logo_path":null,"name":"Norsk Fjernsyn","origin_country":"NO"},{"id":88269,"logo_path":"/ruFAjeHkSB21b535JMzpu6ulioN.png","name":"Story House Productions","origin_country":"DE"},{"id":4606,"logo_path":"/otZHbf1HmzLRQsZFSqJXkf8EHz7.png","name":"ZDF","origin_country":"DE"}],"production_countries":[{"iso_3166_1":"DE","name":"Germany"},{"iso_3166_1":"NO","name":"Norway"}],"release_date":"2019-03-27","revenue":0,"runtime":102,"spoken_languages":[{"english_name":"English","iso_639_1":"en","name":"English"},{"english_name":"Korean","iso_639_1":"ko","name":"한국어/조선말"}],"status":"Released","tagline":"","title":"War of Art","video":false,"vote_average":8.0,"vote_count":1}