{"adult":true,"backdrop_path":null,"belongs_to_collection":null,"budget":0,"genres":[],"homepage":"","id":633779,"imdb_id":"tt5155866","original_language":"en","original_title":"Work Loads 2","overview":"Raw Fuck Club is back with another fresh take on sex life in the modern office, where your boss might a prick, but at least that prick is 8\" long and fucking you raw on his desk. You might have to work late, but at least the cleaning crew has a nice way of saying thanks with a couple of juicy loads. Lazy coworkers? That's OK, as long as they suck dick good, we'll let that slide. Working hard, or hardly working? You decide in Work Loads 2!","popularity":0.6,"poster_path":"/netFIfCNx0Yt4gLuGXXNvAlh571.jpg","production_companies":[{"id":37695,"logo_path":"/9KYNLKCA5Ag4pJeunIcnn7YqELc.png","name":"Dark Alley Media","origin_country":"US"},{"id":118413,"logo_path":"/bJDKqX0EYRRBRTbTjTT7HekkCUD.png","name":"Raw Fuck Club","origin_country":"US"}],"production_countries":[{"iso_3166_1":"US","name":"United States of America"}],"release_date":"2013-05-21","revenue":0,"runtime":106,"spoken_languages":[{"english_name":"English","iso_639_1":"en","name":"English"}],"status":"Released","tagline":"","title":"Work Loads 2","video":false,"vote_average":0.0,"vote_count":0}