{"adult":false,"backdrop_path":null,"belongs_to_collection":null,"budget":0,"genres":[],"homepage":"","id":695741,"imdb_id":null,"original_language":"en","original_title":"Personality Nodes","overview":"Installation constructs every stage of human development as a separate. It visualizes and merges external and internal influences, ranging from birth to twenty-five years of age. That information creates an abstract notion of flows, arrangements, connections and relationships which are influencing a man. Final animated composition is constructed like one piece which contains four different parts.","popularity":0.6,"poster_path":"/9kYciyr2QygmjBmEeRKQ5AMqiRm.jpg","production_companies":[],"production_countries":[],"release_date":"2012-06-30","revenue":0,"runtime":4,"spoken_languages":[],"status":"Released","tagline":"","title":"Personality Nodes","video":false,"vote_average":0.0,"vote_count":0}