{"adult":false,"backdrop_path":null,"belongs_to_collection":null,"budget":0,"genres":[{"id":99,"name":"Documentary"}],"homepage":"","id":702854,"imdb_id":"tt3488460","original_language":"en","original_title":"Rumble on the Lot: Walter Hill's Streets of Fire Revisited","overview":"Walter Hill's Streets of Fire Revisited","popularity":0.844,"poster_path":"/f3aslkKSbzybEAcQFJTjWwZmMSI.jpg","production_companies":[],"production_countries":[],"release_date":"2013-11-08","revenue":0,"runtime":80,"spoken_languages":[{"english_name":"English","iso_639_1":"en","name":"English"}],"status":"Released","tagline":"","title":"Rumble on the Lot: Walter Hill's Streets of Fire Revisited","video":false,"vote_average":0.0,"vote_count":0}