{"adult":false,"backdrop_path":"/iS9yVZ1nnP3to06vECUbgbKCCfj.jpg","belongs_to_collection":null,"budget":0,"genres":[{"id":10749,"name":"Romance"}],"homepage":"","id":704884,"imdb_id":null,"original_language":"ja","original_title":"乱宴の宿 湯けむり未亡人","overview":"Komiya is worried that he can't fit into a woman's hole with a big cock. I finally drop the club woman Mai, but when I bet, the things don't fit and I feel depressed. A few days later, he went to the grave of his dead wife and met Kyoko, the widow who runs the inn. Komiya who decided to stay at her inn had a good atmosphere with Nakaumi Mayumi. Kyoko was very curious when she heard the story of Komiya's big cock from Mayumi. Did you get into work and break into Komiya's room? !","popularity":0.846,"poster_path":"/4Xd0m6Jp7l3CnKnhWnQJeyz0EgB.jpg","production_companies":[],"production_countries":[],"release_date":"2016-04-17","revenue":0,"runtime":60,"spoken_languages":[],"status":"Released","tagline":"","title":"Yukemuri Widow Ryokan no Yado","video":false,"vote_average":0.0,"vote_count":0}