{"adult":false,"backdrop_path":null,"belongs_to_collection":null,"budget":0,"genres":[{"id":99,"name":"Documentary"}],"homepage":"","id":769238,"imdb_id":"tt10417582","original_language":"en","original_title":"Real Kashmir FC","overview":"Davie Robertson - former Aberdeen, Rangers and Leeds United stalwart - is a long way from home. In fact, he's a long way from anywhere. He's the new manager of Real Kashmir FC, and he's left behind his wife and a luxury lifestyle he earned from football, to live in a shared house in a city that regularly suffers violent protests and terrorist attacks. For the people of Kashmir and the owners of the club, Sandeep and Shamim football is not just sport. It's a hope for a better future.","popularity":0.601,"poster_path":null,"production_companies":[{"id":3712,"logo_path":"/7PdJYn2l0iBViud7oqxRHO9UEIR.png","name":"BBC Scotland","origin_country":"GB"},{"id":144567,"logo_path":null,"name":"Bodhi Media","origin_country":""},{"id":76060,"logo_path":null,"name":"Matchlight","origin_country":"GB"}],"production_countries":[{"iso_3166_1":"GB","name":"United Kingdom"}],"release_date":"2019-02-26","revenue":0,"runtime":58,"spoken_languages":[],"status":"Released","tagline":"","title":"Real Kashmir FC","video":false,"vote_average":0.0,"vote_count":0}