{"adult":false,"backdrop_path":"/gvc39zvEzktnQ9mF2yT5nyf4rYh.jpg","belongs_to_collection":null,"budget":0,"genres":[{"id":28,"name":"Action"}],"homepage":"","id":779559,"imdb_id":"tt8792158","original_language":"en","original_title":"Man Eaters","overview":"When it comes to the Man Eaters Bar, looks can kill. And Frank is about to find that out for himself.","popularity":0.6,"poster_path":"/5AxUPR7VQ5mCcGA8yfocEEtEJk4.jpg","production_companies":[],"production_countries":[],"release_date":"2018-07-24","revenue":0,"runtime":3,"spoken_languages":[{"english_name":"English","iso_639_1":"en","name":"English"}],"status":"Released","tagline":"","title":"Man Eaters","video":false,"vote_average":6.0,"vote_count":1}