{"adult":false,"backdrop_path":"/A39dTRGjFpsitYZa5uzQopEJb4m.jpg","belongs_to_collection":null,"budget":0,"genres":[{"id":99,"name":"Documentary"}],"homepage":"","id":809130,"imdb_id":"tt5773400","original_language":"pt","original_title":"Madrepérola","overview":"","popularity":0.625,"poster_path":"/yKLlpbighHJZv09iiMzsMFah2NE.jpg","production_companies":[{"id":67251,"logo_path":null,"name":"Unisinos","origin_country":""}],"production_countries":[],"release_date":"2015-08-08","revenue":0,"runtime":0,"spoken_languages":[],"status":"Released","tagline":"","title":"Madrepérola","video":false,"vote_average":10.0,"vote_count":1}