{"adult":false,"backdrop_path":null,"belongs_to_collection":null,"budget":0,"genres":[],"homepage":"","id":857893,"imdb_id":null,"original_language":"en","original_title":"CKY: Chopped & Sliced","overview":"Infiltrate•Destroy•Rebuild: The Video Album bonus disc! From the late 90's into the new millennium the 'mainstream' attempted to destroy Rock & Roll. Now, Rock & Roll Infiltrates, Destroys & Rebuilds the 'mainstream' I.D.R. The video album is a full-length collection of 12 music videos plus a whole lot more from CKY, the entity that started the destruction of mainstream Rock & Roll during the era of terror...","popularity":0.6,"poster_path":"/4rDWoNnZqhEpITsmEfnK9692No3.jpg","production_companies":[],"production_countries":[],"release_date":"2003-06-15","revenue":0,"runtime":176,"spoken_languages":[],"status":"Released","tagline":"","title":"CKY: Chopped & Sliced","video":false,"vote_average":0.0,"vote_count":0}