{"adult":false,"backdrop_path":null,"belongs_to_collection":null,"budget":0,"genres":[{"id":99,"name":"Documentary"}],"homepage":"","id":859341,"imdb_id":null,"original_language":"de","original_title":"Chernobyl","overview":"","popularity":1.4,"poster_path":"/kVTz8T718i74RZb9lQ4v2EeKfKV.jpg","production_companies":[],"production_countries":[],"release_date":"2005-01-01","revenue":0,"runtime":0,"spoken_languages":[],"status":"Released","tagline":"","title":"Chernobyl","video":false,"vote_average":7.0,"vote_count":1}