{"adult":false,"backdrop_path":null,"belongs_to_collection":null,"budget":0,"genres":[],"homepage":"","id":942239,"imdb_id":"tt2922264","original_language":"ko","original_title":"Boy","overview":"Winter 1988 - Middle school student Jin-Woo (Yeon Jun-Suk) lives with his unemployed alcoholic father (Ahn Nae-Sang) and his unhappy mother (Kim So-Hee) who frequently attempts to runaway from home due to her unhappiness with her husband. Jin-Woo's older sister (Ryu Hyun-Kyung) does whatever she wants and fumes at her mother for the life she lives. Jin-Woo feels sorry for his mom who has to support the family alone and starts to work as a newspaper delivery boy.","popularity":0.6,"poster_path":"/pJhykWjekoXmAVPaSY6qcvvDfzJ.jpg","production_companies":[],"production_countries":[],"release_date":"2011-06-02","revenue":0,"runtime":112,"spoken_languages":[{"english_name":"Korean","iso_639_1":"ko","name":"한국어/조선말"}],"status":"Released","tagline":"","title":"Boy","video":false,"vote_average":0.0,"vote_count":0}