{"adult":false,"backdrop_path":null,"belongs_to_collection":null,"budget":0,"genres":[],"homepage":"","id":964074,"imdb_id":null,"original_language":"es","original_title":"Reyna","overview":"This is what you get for being a faggot, he was told after a beating and fear took hold of him. However, inside his body he found Nina, an ally with exuberant make-up and twenty-centimeter heels, who taught him to fight for the desire for freedom.","popularity":0.6,"poster_path":"/hwAU3tIxu4Cforne4DV1wd2lyjl.jpg","production_companies":[],"production_countries":[],"release_date":"2022-02-14","revenue":0,"runtime":23,"spoken_languages":[{"english_name":"Spanish","iso_639_1":"es","name":"Español"}],"status":"Released","tagline":"","title":"Reyna","video":false,"vote_average":0.0,"vote_count":0}