{"adult":false,"backdrop_path":"/e9eGV4rDrX549mDAl1GYQDqoNm4.jpg","belongs_to_collection":null,"budget":1000,"genres":[{"id":27,"name":"Horror"},{"id":18,"name":"Drama"}],"homepage":"","id":1026772,"imdb_id":"tt13555924","original_language":"en","original_title":"The Dead Sleep Soundly","overview":"We follow the story of a man as he attempts to reconcile with his dark past. His nightly insomnia leads him to people watching around the city.","popularity":0.6,"poster_path":"/c1LozyMFCe09SRk1MDTCKhPsqVP.jpg","production_companies":[{"id":125200,"logo_path":null,"name":"Fame Cinema","origin_country":""}],"production_countries":[],"release_date":"2021-10-30","revenue":0,"runtime":65,"spoken_languages":[{"english_name":"English","iso_639_1":"en","name":"English"}],"status":"Released","tagline":"","title":"The Dead Sleep Soundly","video":false,"vote_average":0.0,"vote_count":0}