{"adult":false,"backdrop_path":null,"belongs_to_collection":null,"budget":0,"genres":[{"id":10749,"name":"Romance"},{"id":10402,"name":"Music"}],"homepage":"","id":272999,"imdb_id":"tt0024900","original_language":"en","original_title":"Blossom Time","overview":"World-renowned tenor Richard Tauber features in a dramatisation of the life of Schubert, focusing on the composer's unrequited love for a dance master's daughter.","popularity":0.962,"poster_path":"/y84S4wTwRgTNfnLjlyPWk22YPFC.jpg","production_companies":[{"id":305,"logo_path":null,"name":"British International Pictures","origin_country":"GB"}],"production_countries":[{"iso_3166_1":"GB","name":"United Kingdom"}],"release_date":"1934-01-01","revenue":0,"runtime":87,"spoken_languages":[{"english_name":"English","iso_639_1":"en","name":"English"}],"status":"Released","tagline":"","title":"Blossom Time","video":true,"vote_average":4.8,"vote_count":4}