{"adult":false,"backdrop_path":"/vBtBmRUFoB5TmqmkAdTix3u94pk.jpg","belongs_to_collection":null,"budget":0,"genres":[{"id":10749,"name":"Romance"},{"id":18,"name":"Drama"}],"homepage":"","id":365356,"imdb_id":"tt0179783","original_language":"sh","original_title":"Drugarčine","overview":"The war is over, and a group of young Partisans returns to their town to continue their interrupted education. They are doing everything in their way, because they are young enough to go to school and to horse around, but mature enough to react to lies and injustice. Loud, ready to fight, they are a problem in school, in youth organization, in town's command. And when they get used to normal life, one of them gets killed by Chetnik renegades' ambush. The comrades wear their uniforms again, take their weapons and succeed in revenging their comrade. When they return to school again, they are determined to pass the maturity test as well...","popularity":0.6,"poster_path":"/mKE1ybrkgE8JVx7bWbAP742kF0X.jpg","production_companies":[{"id":5940,"logo_path":null,"name":"Avala Film","origin_country":"RS"},{"id":28221,"logo_path":null,"name":"Beograd Film","origin_country":"RS"},{"id":44449,"logo_path":null,"name":"Kinema Sarajevo","origin_country":"BA"}],"production_countries":[{"iso_3166_1":"YU","name":"Yugoslavia"}],"release_date":"1979-01-01","revenue":0,"runtime":96,"spoken_languages":[{"english_name":"Serbian","iso_639_1":"sr","name":"Srpski"}],"status":"Released","tagline":"","title":"The Pals","video":false,"vote_average":4.2,"vote_count":4}