{"adult":false,"backdrop_path":"/4BjYtJ9lHqvl4XFqKRX1ofyVBzf.jpg","belongs_to_collection":{"id":375820,"name":"Collection Les 3 p'tits cochons","poster_path":"/kXrFiNczlwesFPzJhxm3VQalyun.jpg","backdrop_path":"/tnYiwXs9Pk7RGqtBcg4pdyOzOpj.jpg"},"budget":0,"genres":[{"id":35,"name":"Comedy"}],"homepage":"","id":375812,"imdb_id":"tt5097398","original_language":"fr","original_title":"Les 3 p'tits cochons 2","overview":"Rémy is always between two planes, travels to Shanghai on business. During this trip, he takes the opportunity to cheat Dominique first with a woman, then with a man. Upon his return, his wife puts him out after showing him more than compromising photos of his Asian aspirations.","popularity":1.856,"poster_path":"/vEKaNZrBcmpWHDREUfPlBiek1XW.jpg","production_companies":[{"id":79468,"logo_path":null,"name":"Bloom Films","origin_country":"CA"},{"id":749,"logo_path":null,"name":"Christal Films","origin_country":"CA"}],"production_countries":[{"iso_3166_1":"CA","name":"Canada"}],"release_date":"2016-07-01","revenue":0,"runtime":102,"spoken_languages":[{"english_name":"French","iso_639_1":"fr","name":"Français"}],"status":"Released","tagline":"","title":"The 3 L'il Pigs 2","video":false,"vote_average":5.8,"vote_count":13}