{"adult":false,"backdrop_path":"/lGQf5gkyAmlDflwnGSI4W9EfRIB.jpg","belongs_to_collection":null,"budget":0,"genres":[{"id":53,"name":"Thriller"}],"homepage":"","id":398636,"imdb_id":"tt4943558","original_language":"bn","original_title":"সাহেব বিবি গোলাম","overview":"Three very different people from three very different worlds collide one winter afternoon in an anarchic Kolkata.","popularity":1.582,"poster_path":"/hRYk2DksR1BwZmUfiakhqw7QDVa.jpg","production_companies":[{"id":164188,"logo_path":null,"name":"Friends Communication","origin_country":"IN"}],"production_countries":[{"iso_3166_1":"IN","name":"India"}],"release_date":"2016-05-22","revenue":0,"runtime":121,"spoken_languages":[{"english_name":"Bengali","iso_639_1":"bn","name":"বাংলা"}],"status":"Released","tagline":"","title":"Saheb Bibi Golaam","video":false,"vote_average":6.3,"vote_count":3}