{"adult":false,"backdrop_path":null,"belongs_to_collection":null,"budget":0,"genres":[{"id":99,"name":"Documentary"}],"homepage":"","id":499185,"imdb_id":"tt1552990","original_language":"fr","original_title":"Fleurs dans le miroir, lune dans l'eau","overview":"The title of the François Lunel film is the Buddhist proverb concluding by: \"all is but illusion\". His movie draws the Tsai Ming-Liang's face during the shooting of his movie Visage, which itself is also a movie within a movie.","popularity":0.6,"poster_path":null,"production_companies":[{"id":8041,"logo_path":null,"name":"Homegreen Films","origin_country":"TW"},{"id":34766,"logo_path":"/atA5jWdLJ5tgyKQ5dJ6FcYLQsUo.png","name":"Musée du Louvre","origin_country":"FR"},{"id":3883,"logo_path":null,"name":"JBA Production","origin_country":"FR"}],"production_countries":[{"iso_3166_1":"FR","name":"France"},{"iso_3166_1":"TW","name":"Taiwan"}],"release_date":"2009-06-28","revenue":0,"runtime":48,"spoken_languages":[{"english_name":"English","iso_639_1":"en","name":"English"},{"english_name":"Mandarin","iso_639_1":"zh","name":"普通话"},{"english_name":"French","iso_639_1":"fr","name":"Français"}],"status":"Released","tagline":"","title":"Flowers in the Mirror, Moon in the Water","video":false,"vote_average":0.0,"vote_count":0}