{"adult":false,"backdrop_path":null,"belongs_to_collection":null,"budget":0,"genres":[],"homepage":"","id":546959,"imdb_id":"tt1579551","original_language":"en","original_title":"Hello Guru","overview":"1996 film starring Aamani, Shobhan Babu, Brahmanandam. It had a budget of INR 23,000,000 (approx)","popularity":0.6,"poster_path":null,"production_companies":[],"production_countries":[],"release_date":"","revenue":0,"runtime":0,"spoken_languages":[],"status":"Released","tagline":"","title":"Hello Guru","video":false,"vote_average":0.0,"vote_count":0}