{"adult":false,"backdrop_path":null,"belongs_to_collection":null,"budget":0,"genres":[{"id":35,"name":"Comedy"}],"homepage":"","id":560985,"imdb_id":"tt0156466","original_language":"fr","original_title":"Des quintuplés au pensionnat","overview":"In a girls boarding-school run by Madame Piégeois,young Gisèle meets, at night, the count of Champrès 's son.","popularity":1.091,"poster_path":"/kWGmAycngzatBitj4gZ0uyYT6R1.jpg","production_companies":[{"id":8130,"logo_path":null,"name":"Jad Films","origin_country":""}],"production_countries":[{"iso_3166_1":"FR","name":"France"}],"release_date":"1953-05-08","revenue":0,"runtime":0,"spoken_languages":[{"english_name":"French","iso_639_1":"fr","name":"Français"}],"status":"Released","tagline":"","title":"Des quintuplés au pensionnat","video":false,"vote_average":0.0,"vote_count":0}