{"adult":false,"backdrop_path":"/8qE8lsSCXxqMyDzP0cnkLSa8d4J.jpg","belongs_to_collection":null,"budget":6754,"genres":[{"id":18,"name":"Drama"},{"id":28,"name":"Action"}],"homepage":"http://wwr-stardom.com/","id":599278,"imdb_id":"tt9649494","original_language":"en","original_title":"Stardom New Year Stars Day 1","overview":"Triple Threat Match Natsuko Tora vs Kaori Yoneyama and Alex Gracia. 3 On 1 Handicap Match Viper vs Hanan, Rina and Hina. Tag Team Match Sadie Gibbs and Mari Apache vs Jungle Assault Nation (Jungle Kyona and Ruaka). 6 Woman Tag Team Match Oedo-tai (Natsu Sumire, Hazuki and Kagetsu) vs Jamie Hayter, Hana Kimura and Bobbi Tyler. 10 Woman Elimination Tag Team Match Queen's Quest (Bea Priestley, Utami Hayashishita, Momo Watanabe, AZM and Konami) vs Saki Kashia, Starlight Kid, Arisa Hoshiki, Tam Nakano and Natsumi.","popularity":0.881,"poster_path":"/zmClrh3NBZcdv9UObuEuT6ftUJ2.jpg","production_companies":[{"id":118180,"logo_path":"/gTEbqOLuwGCzn6rYUTLMLuArk2K.png","name":"World Wonder Ring Stardom","origin_country":"JP"}],"production_countries":[{"iso_3166_1":"JP","name":"Japan"}],"release_date":"2019-01-02","revenue":22342,"runtime":132,"spoken_languages":[{"english_name":"Japanese","iso_639_1":"ja","name":"日本語"}],"status":"Released","tagline":"","title":"Stardom New Year Stars Day 1","video":true,"vote_average":7.0,"vote_count":1}