{"adult":false,"backdrop_path":"/4LtA7EoD2MsERKrhVviWacgrveA.jpg","belongs_to_collection":null,"budget":0,"genres":[{"id":18,"name":"Drama"}],"homepage":"","id":615248,"imdb_id":"tt12380182","original_language":"pt","original_title":"A Mulher que Sou","overview":"Marta wants to give herself a chance to live a new life, in a new city.","popularity":0.603,"poster_path":"/mLLibQlVSz5C7dgucZkZMy6WxKd.jpg","production_companies":[],"production_countries":[{"iso_3166_1":"BR","name":"Brazil"}],"release_date":"2019-08-28","revenue":0,"runtime":15,"spoken_languages":[{"english_name":"Portuguese","iso_639_1":"pt","name":"Português"}],"status":"Released","tagline":"","title":"A Mulher que Sou","video":false,"vote_average":0.0,"vote_count":0}