{"adult":false,"backdrop_path":"/lKUGDhvQqFgSEQsXOvqy0UBhbsJ.jpg","belongs_to_collection":null,"budget":0,"genres":[{"id":37,"name":"Western"}],"homepage":"","id":616948,"imdb_id":"tt0012261","original_language":"en","original_title":"Hearts Up","overview":"Coming upon a burning cabin, David Brent discovers the body of Jim Drew, who had been killed in a fight with a drunken Indian. Brent finds in Drew's pocket a letter announcing the impending arrival of Drew's daughter Lorelei. Feeling an obligation to Drew, who once saved his life, Brent journeys to San Francisco to meet Lorelei, who mistakes him for her father. Brent cannot bring himself to break the bad news to her and does not correct her false assumption.","popularity":0.6,"poster_path":"/uAPeoqZU2UvQZm7fOe5m3qQXRpk.jpg","production_companies":[{"id":13133,"logo_path":null,"name":"Universal Film Manufacturing Company","origin_country":"US"}],"production_countries":[{"iso_3166_1":"US","name":"United States of America"}],"release_date":"1921-01-02","revenue":0,"runtime":50,"spoken_languages":[{"english_name":"No Language","iso_639_1":"xx","name":"No Language"}],"status":"Released","tagline":"","title":"Hearts Up","video":false,"vote_average":0.0,"vote_count":0}