{"adult":false,"backdrop_path":"/3v6J6pVrNUdncsFfHB3ygtF4sfE.jpg","belongs_to_collection":null,"budget":0,"genres":[{"id":99,"name":"Documentary"}],"homepage":"https://firstweeat.ca/","id":713232,"imdb_id":"tt13321770","original_language":"en","original_title":"First We Eat","overview":"Putting food security to the test in Yukon, the filmmaker bans all store-bought groceries from her house in a year-long adventure in farming, fishing and foraging complicated by three skeptical teenagers, no caffeine and -40° temperatures.","popularity":1.024,"poster_path":"/8JLilF83VUeBs5pK5471f0AwtrC.jpg","production_companies":[],"production_countries":[{"iso_3166_1":"CA","name":"Canada"}],"release_date":"2020-05-28","revenue":0,"runtime":101,"spoken_languages":[{"english_name":"English","iso_639_1":"en","name":"English"}],"status":"Released","tagline":"The 100 Mile Diet — Yukon Style","title":"First We Eat","video":false,"vote_average":8.0,"vote_count":1}