{"adult":false,"backdrop_path":null,"belongs_to_collection":null,"budget":0,"genres":[{"id":18,"name":"Drama"}],"homepage":"","id":730720,"imdb_id":"tt13900818","original_language":"fr","original_title":"Les Épisodes - Printemps 2018","overview":"Marta, Luc and Charlotte, aged twenty-five to thirty-years old, have a lot to share in the city of Paris: friendships, demands and refusals. Ideas grow in the occupied university departments. THE EPISODES - SPRING 2018 is so singular in its approach to existence and so sovereign in the way it establishes its own language that all attempts at defining, assigning a genre or a previously identified aspect of film, are doomed to failure. All we have to do is open up the dictionary: after all, that was Ponge’s reaction when confronting the unknown. « Episode. A work’s division including several parts, each forming a self-sufficient whole. A more or less striking moment in a lifetime. A set of actions, of events forming a whole and making up a striking moment in history or time. »","popularity":0.6,"poster_path":"/87s0QFiwOOVcWSpe5bi63UbOMPv.jpg","production_companies":[{"id":87071,"logo_path":"/xNscZFL4i3tX1dPJHs6hKIErc3C.png","name":"Société Acéphale","origin_country":"FR"}],"production_countries":[{"iso_3166_1":"FR","name":"France"}],"release_date":"2020-07-24","revenue":0,"runtime":30,"spoken_languages":[{"english_name":"Spanish","iso_639_1":"es","name":"Español"},{"english_name":"French","iso_639_1":"fr","name":"Français"}],"status":"Released","tagline":"","title":"Episodes - Spring 2018","video":false,"vote_average":0.0,"vote_count":0}