{"adult":false,"backdrop_path":null,"belongs_to_collection":null,"budget":0,"genres":[{"id":18,"name":"Drama"},{"id":28,"name":"Action"}],"homepage":"","id":80836,"imdb_id":"tt0944185","original_language":"en","original_title":"Andhrudu","overview":"Surendra (T. Gopichand) is an honest and hot-blooded cop. Archana (Gowri Pandit) is the daughter of police commissioner. They meet accidentally and their relationship blossoms into love. Archana's father is of Bihar origin. Parents settle the match of Surendra and Archana. When they are about to get engaged, Surendra expresses his reservations due to Archana overhearing her father's conversation with his long estranged sister on the subject of Archana and Sinha marrying. Surendra takes the blame for the destroyed relationship and Archana goes back to Bihar to wed her cousin Sinha (Salim Baig). The rest of the story is all about how Surendra goes to Bihar and wins Archana back.","popularity":2.196,"poster_path":"/bwcKk2HaKIaGxqYVdLn3HoMsrHw.jpg","production_companies":[],"production_countries":[],"release_date":"2005-08-19","revenue":0,"runtime":150,"spoken_languages":[{"english_name":"Telugu","iso_639_1":"te","name":"తెలుగు"}],"status":"Released","tagline":"","title":"Andhrudu","video":false,"vote_average":7.0,"vote_count":5}