{"adult":true,"backdrop_path":null,"belongs_to_collection":null,"budget":0,"genres":[],"homepage":"","id":898020,"imdb_id":null,"original_language":"fr","original_title":"Anal Beauty 3","overview":"TUSHY.com proudly presents the third installment of \"Anal Beauty,\" captured by 2016 AVN Award winning Director of the Year, Greg Lansky. Watch amazing natural beauty Alex Grey's very first anal scene! You will be impressed by her passionate performance. Also, blonde teen Arya loses her anal virginity; Kelsi's big booty shows her love for anal and finally famous Gracie Glam in a rare and intense anal scene. All scenes feature real scripted stories leading to cinematically shot sex like you won't find anywhere else! This movie is about quality. You will appreciate the attention to detail with the luxury and high-end production values.","popularity":0.6,"poster_path":"/sfydEM6HsAi4kfpu5mG2skvxaR7.jpg","production_companies":[{"id":72478,"logo_path":"/ys62nmoU2CldxoA2l2Q8UuLcsRJ.png","name":"Tushy","origin_country":"US"}],"production_countries":[],"release_date":"2016-01-01","revenue":0,"runtime":0,"spoken_languages":[{"english_name":"English","iso_639_1":"en","name":"English"}],"status":"Released","tagline":"","title":"Anal Beauty 3","video":false,"vote_average":0.0,"vote_count":0}